odoo10_addon_medical_practitioner_us-10.0.1.0.0-py2.7-nspkg.pth
odoo/addons/medical_practitioner_us/README.rst
odoo/addons/medical_practitioner_us/__init__.py
odoo/addons/medical_practitioner_us/__manifest__.py
odoo/addons/medical_practitioner_us/data/res_partner_id_category.xml
odoo/addons/medical_practitioner_us/models/__init__.py
odoo/addons/medical_practitioner_us/models/res_partner.py
odoo/addons/medical_practitioner_us/static/description/icon.png
odoo/addons/medical_practitioner_us/tests/__init__.py
odoo/addons/medical_practitioner_us/tests/test_medical_practitioner.py
odoo/addons/medical_practitioner_us/views/medical_practitioner.xml
odoo10_addon_medical_practitioner_us-10.0.1.0.0.dist-info/DESCRIPTION.rst
odoo10_addon_medical_practitioner_us-10.0.1.0.0.dist-info/METADATA
odoo10_addon_medical_practitioner_us-10.0.1.0.0.dist-info/RECORD
odoo10_addon_medical_practitioner_us-10.0.1.0.0.dist-info/WHEEL
odoo10_addon_medical_practitioner_us-10.0.1.0.0.dist-info/metadata.json
odoo10_addon_medical_practitioner_us-10.0.1.0.0.dist-info/namespace_packages.txt
odoo10_addon_medical_practitioner_us-10.0.1.0.0.dist-info/top_level.txt
